automation_scripts/__init__.py
automation_scripts/account_orchestration/__init__.py
automation_scripts/account_orchestration/account_data_script_manager.py
automation_scripts/account_orchestration/accounts_data.py
automation_scripts/current_event_script/__init__.py
automation_scripts/current_event_script/christmas_script.py
automation_scripts/current_event_script/easter_script.py
automation_scripts/current_event_script/independence_script.py
automation_scripts/current_event_script/muertos_script.py
automation_scripts/current_event_script/oktoberfest_script.py
automation_scripts/default_script/__init__.py
automation_scripts/default_script/script.py
automation_scripts/default_script/script_data.py
automation_scripts/default_script/script_json_schema.json
automation_scripts/default_script/script_scheduler.py
automation_scripts/example_scripts/__init__.py
automation_scripts/example_scripts/cycle_hourly_jobs.py
automation_scripts/example_scripts/solve_daily_quests_script.py
automation_scripts/example_scripts/work_cycle_v1.py
automation_scripts/exp_gain_script/__init__.py
automation_scripts/exp_gain_script/example_exp_scripts/__init__.py
automation_scripts/exp_gain_script/example_exp_scripts/cycle_script_v1.py
automation_scripts/exp_gain_script/example_exp_scripts/loader_func_v1.py
automation_scripts/exp_gain_script/example_exp_scripts/sleep_func_v1.py
automation_scripts/exp_gain_script/exp_script.py
automation_scripts/exp_gain_script/exp_script_executor.py
automation_scripts/exp_gain_script/exp_script_load.py
automation_scripts/exp_gain_script/greedy_exp_gain/__init.py
automation_scripts/farm_event/__init__.py
automation_scripts/farm_event/event_drop_script.py
automation_scripts/farm_event/farm_script.py
automation_scripts/inifinite_duels/__init__.py
automation_scripts/inifinite_duels/duel_manager_state.py
automation_scripts/inifinite_duels/duel_npc_rule.py
automation_scripts/inifinite_duels/duel_reset_manager.py
automation_scripts/inifinite_duels/duel_settings.py
python_the_west-0.2.1.dist-info/LICENSE
python_the_west-0.2.1.dist-info/METADATA
python_the_west-0.2.1.dist-info/WHEEL
python_the_west-0.2.1.dist-info/RECORD
