Metadata-Version: 2.1
Name: python-the-west
Version: 0.2.1
Summary: Interact with the browser game 'The west' programatically using http requests.
Author: MariusSilviuHriscu
Author-email: hriscumarius65536@gmail.com
Requires-Python: >=3.11,<4.0
Classifier: Programming Language :: Python :: 3
Classifier: Programming Language :: Python :: 3.11
Requires-Dist: bidict (>=0.22.1,<0.23.0)
Requires-Dist: bs4 (>=0.0.1,<0.0.2)
Requires-Dist: dateparser (>=1.1.8,<2.0.0)
Requires-Dist: jupyter (>=1.0.0,<2.0.0)
Requires-Dist: matplotlib (>=3.8.2,<4.0.0)
Requires-Dist: numpy (>=1.25.2,<2.0.0)
Requires-Dist: pydantic (>=2.8.2,<3.0.0)
Requires-Dist: pysocks (>=1.7.1,<2.0.0)
Requires-Dist: requests (>=2.31.0,<3.0.0)
Requires-Dist: sqlalchemy (>=2.0.25,<3.0.0)
Requires-Dist: stem (>=1.8.2,<2.0.0)
